qclient/__init__.py
qclient/qclient.py
qclient/test.py
qclient-1.0.6.dist-info/LICENSE
qclient-1.0.6.dist-info/METADATA
qclient-1.0.6.dist-info/WHEEL
qclient-1.0.6.dist-info/top_level.txt
qclient-1.0.6.dist-info/RECORD
