Metadata-Version: 2.1
Name: qclient
Version: 1.0.6
Summary: Client for executing quantum applications on QServer instances
Home-page: https://github.com/ax1/qclient_py
Author: ax1
Author-email: 
License: UNKNOWN
Project-URL: Bug Tracker, https://github.com/ax1/qclient_py/issues
Platform: UNKNOWN
Classifier: Programming Language :: Python :: 3
Classifier: License :: OSI Approved :: MIT License
Classifier: Operating System :: OS Independent
Requires-Python: >=3.6
License-File: LICENSE
